certbot_dns_rockenstein/__init__.py
certbot_dns_rockenstein/_internal/__init__.py
certbot_dns_rockenstein/_internal/dns_rockenstein.py
certbot_dns_rockenstein/_internal/rox_api.py
certbot_dns_rockenstein-1.0.0.dist-info/LICENSE
certbot_dns_rockenstein-1.0.0.dist-info/METADATA
certbot_dns_rockenstein-1.0.0.dist-info/WHEEL
certbot_dns_rockenstein-1.0.0.dist-info/entry_points.txt
certbot_dns_rockenstein-1.0.0.dist-info/top_level.txt
certbot_dns_rockenstein-1.0.0.dist-info/RECORD
